gitlab_wiki_edit_url/__init__.py
gitlab_wiki_edit_url/plugin.py
mkdocs_gitlab_wiki_edit_url-0.0.2.dist-info/licenses/LICENSE
mkdocs_gitlab_wiki_edit_url-0.0.2.dist-info/METADATA
mkdocs_gitlab_wiki_edit_url-0.0.2.dist-info/WHEEL
mkdocs_gitlab_wiki_edit_url-0.0.2.dist-info/entry_points.txt
mkdocs_gitlab_wiki_edit_url-0.0.2.dist-info/top_level.txt
mkdocs_gitlab_wiki_edit_url-0.0.2.dist-info/RECORD
