Metadata-Version: 2.4
Name: mkdocs-gitlab-wiki-edit-url
Version: 0.0.2
Summary: MkDocs plugin for using Edit URLs compatible with Gitlab Wiki
Home-page: https://github.com/auke-/mkdocs-gitlab-wiki-edit-url
Author: Auke Schrijnen
Author-email: Auke Schrijnen <auke@schrijnen.nl>
License-Expression: MIT
Project-URL: Homepage, https://github.com/auke-/mkdocs-gitlab-wiki-edit-url
Project-URL: Issues, https://github.com/auke-/mkdocs-gitlab-wiki-edit-url/issues
Classifier: Programming Language :: Python :: 3
Classifier: Operating System :: OS Independent
Requires-Python: >=3.9
License-File: LICENSE
Dynamic: author
Dynamic: home-page
Dynamic: license-file
